{
  "name": "风暴遗迹",
  "startPosition": { "x": 0, "y": 4, "z": 0 },
  "platforms": [
    { "x": 0, "y": 1, "z": 0, "width": 10, "depth": 10, "height": 0.5, "tooltip": "遗迹入口" },
    { "x": -14, "y": 3, "z": -14, "width": 4, "depth": 4, "height": 0.5, "tooltip": "" },
    { "x": 14, "y": 3, "z": -14, "width": 4, "depth": 4, "height": 0.5, "tooltip": "" },
    { "x": [-12, 12], "y": 5, "z": -24, "width": 3, "depth": 3, "height": 0.5, "speed": 0.55, "tooltip": "移动平台" },
    { "x": 0, "y": 7, "z": -36, "width": 6, "depth": 6, "height": 0.5, "tooltip": "" },
    { "x": -20, "y": 9, "z": -48, "width": 3, "depth": 3, "height": 0.5, "tooltip": "左侧" },
    { "x": 20, "y": 9, "z": -48, "width": 3, "depth": 3, "height": 0.5, "tooltip": "右侧" },
    { "x": -30, "y": [8, 12], "z": -58, "width": 4, "depth": 4, "height": 0.5, "speed": 0.4, "tooltip": "升降左" },
    { "x": 30, "y": [8, 12], "z": -58, "width": 4, "depth": 4, "height": 0.5, "speed": 0.4, "tooltip": "升降右" },
    { "x": 0, "y": 14, "z": -70, "width": 8, "depth": 8, "height": 0.5, "isGoal": true, "tooltip": "" }
  ],
  "walls": [
    { "x": -14, "y": 2, "z": -16, "width": 6, "height": 5, "depth": 0.5 },
    { "x": 14, "y": 2, "z": -16, "width": 6, "height": 5, "depth": 0.5 },
    { "x": -30, "y": 8, "z": -58, "width": 4, "height": 6, "depth": 0.5 },
    { "x": 30, "y": 8, "z": -58, "width": 4, "height": 6, "depth": 0.5 },
    { "x": 0, "y": 10, "z": -48, "width": 16, "height": 4, "depth": 0.5 }
  ],
  "decorations": [
    { "type": "arrow", "x": 0, "y": 1.25, "z": -4, "scale": 0.8, "orientation": "forward" },
    { "type": "arrow", "x": 0, "y": 7.25, "z": -40, "scale": 0.7, "orientation": "up" }
  ]
}